README.txt
buildout.cfg
setup.py
src/zc/__init__.py
src/zc.reloadmonitor.egg-info/PKG-INFO
src/zc.reloadmonitor.egg-info/SOURCES.txt
src/zc.reloadmonitor.egg-info/dependency_links.txt
src/zc.reloadmonitor.egg-info/entry_points.txt
src/zc.reloadmonitor.egg-info/namespace_packages.txt
src/zc.reloadmonitor.egg-info/not-zip-safe
src/zc.reloadmonitor.egg-info/requires.txt
src/zc.reloadmonitor.egg-info/top_level.txt
src/zc/reloadmonitor/__init__.py
src/zc/reloadmonitor/configure.zcml
src/zc/reloadmonitor/tests.py