Metadata-Version: 1.0
Name: zc.reloadmonitor
Version: 0.3.0
Summary: zc.reloadmonitor
Home-page: UNKNOWN
Author: Jim Fulton
Author-email: jim@zope.com
License: ZPL 2.1
Platform: UNKNOWN
